{
 "actions": [],
 "allow_rename": 1,
 "creation": "2024-09-30 21:30:30.988529",
 "doctype": "DocType",
 "editable_grid": 1,
 "engine": "InnoDB",
 "field_order": [
  "project_number",
  "project_name",
  "province",
  "document_value"
 ],
 "fields": [
  {
   "fieldname": "project_number",
   "fieldtype": "Data",
   "in_list_view": 1,
   "in_standard_filter": 1,
   "label": "Project Number"
  },
  {
   "fieldname": "project_name",
   "fieldtype": "Data",
   "in_list_view": 1,
   "in_standard_filter": 1,
   "label": "Project Name"
  },
  {
   "fieldname": "province",
   "fieldtype": "Data",
   "in_list_view": 1,
   "in_standard_filter": 1,
   "label": "Province"
  },
  {
   "fieldname": "document_value",
   "fieldtype": "Currency",
   "in_list_view": 1,
   "in_standard_filter": 1,
   "label": "Document Value"
  }
 ],
 "index_web_pages_for_search": 1,
 "istable": 1,
 "links": [],
 "modified": "2024-09-30 21:32:36.169900",
 "modified_by": "Administrator",
 "module": "team",
 "name": "Project Details",
 "owner": "Administrator",
 "permissions": [],
 "sort_field": "modified",
 "sort_order": "DESC",
 "states": []
}